curo/__init__.py
curo/calculator.py
curo/enums.py
curo/exceptions.py
curo/series.py
curo/utils.py
curo/daycount/__init__.py
curo/daycount/actual_360.py
curo/daycount/actual_365.py
curo/daycount/actual_isda.py
curo/daycount/convention.py
curo/daycount/day_count_factor.py
curo/daycount/eu_2008_48.py
curo/daycount/eu_30_360.py
curo/daycount/uk_conc_app.py
curo/daycount/us_30_360.py
curo/daycount/us_30u_360.py
curo/daycount/us_appendix_j.py
curo-1.0.0.dist-info/licenses/LICENSE
curo-1.0.0.dist-info/METADATA
curo-1.0.0.dist-info/WHEEL
curo-1.0.0.dist-info/top_level.txt
curo-1.0.0.dist-info/RECORD
