Metadata-Version: 2.4
Name: curo
Version: 1.0.0
Summary: A feature-rich library for performing simple to advanced instalment credit financial calculations.
Author: Andrew Murphy
License-Expression: MIT
Project-URL: documentation, https://andrewmurphy353.github.io/curo_python/
Project-URL: source, https://github.com/andrewmurphy353/curo_python.git
Project-URL: changelog, https://github.com/andrewmurphy353/curo_python/blob/main/CHANGELOG.md
Project-URL: issues, https://github.com/andrewmurphy353/curo_python/issues
Keywords: finance,hire purchase,lease,loan,calculator,apr,irr,xirr
Classifier: Intended Audience :: Developers
Classifier: Intended Audience :: Financial and Insurance Industry
Classifier: Natural Language :: English
Classifier: Programming Language :: Python :: 3.11
Classifier: Topic :: Office/Business :: Financial
Requires-Python: >=3.11
License-File: LICENSE
Requires-Dist: numpy>=2.4.0
Requires-Dist: pandas>=2.3.3
Requires-Dist: python-dateutil>=2.9.0.post0
Requires-Dist: scipy>=1.16.3
Provides-Extra: dev
Requires-Dist: pytest>=9.0.2; extra == "dev"
Requires-Dist: pytest-cov>=7.0.0; extra == "dev"
Requires-Dist: coverage>=7.13.0; extra == "dev"
Requires-Dist: twine>=6.2.0; extra == "dev"
Requires-Dist: toml>=0.10.2; extra == "dev"
Requires-Dist: mkdocs>=1.6.1; extra == "dev"
Requires-Dist: mkdocs-material>=9.7.1; extra == "dev"
Requires-Dist: mkdocstrings>=1.0.0; extra == "dev"
Requires-Dist: mkdocstrings-python>=2.0.1; extra == "dev"
Requires-Dist: pymdown-extensions>=10.20; extra == "dev"
Dynamic: license-file
